{
  "last_updated": "2026-02-22T18:20:13.247349",
  "news_count": 25,
  "news": [
    {
      "source": "techcrunch",
      "title": "Quantonation’s double-sized second fund shows quantum still has believers",
      "summary": "Quantonation Ventures, a venture firm investing in quantum and physics-based startups, has closed its oversubscribed second fund at €220 million, or approximately $260 million. That’s more than twice the size of its inaugural fund, and comes in addition to other signals that the quantum winter isn’t",
      "link": "https://techcrunch.com/2026/02/22/quantonations-double-sized-second-fund-shows-quantum-still-has-believers/",
      "published": "Sun, 22 Feb 2026 18:00:00 +0000",
      "keywords": [
        "Startup",
        "AR"
      ],
      "category": "Mobile",
      "crawled_at": "2026-02-22T18:20:12.619949"
    },
    {
      "source": "techcrunch",
      "title": "Trump says Netflix will face ‘consequences’ if it doesn’t fire board member Susan Rice",
      "summary": "Netflix board member Susan Rice had predicted that corporations that “take a knee” to Trump will be “held accountable” when Democrats return to power.",
      "link": "https://techcrunch.com/2026/02/22/trump-says-netflix-will-face-consequences-if-it-doesnt-fire-board-member-susan-rice/",
      "published": "Sun, 22 Feb 2026 17:39:55 +0000",
      "keywords": [
        "AR"
      ],
      "category": "Tech News",
      "crawled_at": "2026-02-22T18:20:12.620004"
    },
    {
      "source": "techcrunch",
      "title": "TechCrunch Mobility: Waymo makes its defense",
      "summary": "Welcome back to TechCrunch Mobility — your central hub for news and insights on the future of transportation.",
      "link": "https://techcrunch.com/2026/02/22/techcrunch-mobility-waymo-makes-its-defense/",
      "published": "Sun, 22 Feb 2026 17:05:00 +0000",
      "keywords": [],
      "category": "Tech News",
      "crawled_at": "2026-02-22T18:20:12.620043"
    },
    {
      "source": "techcrunch",
      "title": "China’s brain-computer interface industry is racing ahead",
      "summary": "China’s brain-computer interface industry is rapidly scaling from research to commercialization, driven by strong policy support, expanding clinical trials, and growing investor interest.",
      "link": "https://techcrunch.com/2026/02/22/chinas-brain-computer-interface-industry-is-racing-ahead/",
      "published": "Sun, 22 Feb 2026 16:00:00 +0000",
      "keywords": [
        "AI",
        "API",
        "REST",
        "AR"
      ],
      "category": "AI/ML",
      "crawled_at": "2026-02-22T18:20:12.620079"
    },
    {
      "source": "techcrunch",
      "title": "6 days left to lock in the lowest TechCrunch Disrupt 2026 rates",
      "summary": "Super Early Bird pricing for TechCrunch Disrupt 2026 ends February 27 at 11:59 p.m. PT. That means you have just 6 days left to secure up to $680 of ticket savings.",
      "link": "https://techcrunch.com/2026/02/22/6-days-left-to-lock-in-the-lowest-techcrunch-disrupt-2026-rates/",
      "published": "Sun, 22 Feb 2026 15:00:00 +0000",
      "keywords": [
        "AR"
      ],
      "category": "Tech News",
      "crawled_at": "2026-02-22T18:20:12.620115"
    },
    {
      "source": "theverge",
      "title": "Trump says Netflix will ‘pay the consequences’ if it doesn’t fire Susan Rice",
      "summary": "Donald Trump threatened that there would be \"consequences\" for Netflix if it didn't fire board member Susan Rice. Rice served in both the Obama and Biden administrations, and recently appeared on Preet Bharara's podcast, where she said corporations that \"take a knee to Trump\" are going to be \"caught",
      "link": "https://www.theverge.com/policy/882881/trump-netflix-consequences-fire-susan-rice",
      "published": "2026-02-22T10:37:41-05:00",
      "keywords": [
        "AI",
        "Go",
        "AR"
      ],
      "category": "AI/ML",
      "crawled_at": "2026-02-22T18:20:12.718247"
    },
    {
      "source": "theverge",
      "title": "This magazine plays Tetris — here’s how",
      "summary": "Tetris has been immortalized in a playable McDonald's plastic chicken nugget, a playable fake 7-Eleven Slurpee cup, and a playable wristwatch. But the most intriguing way to play Tetris yet is encased in paper. Last year the Tetris Company partnered with Red Bull for a gaming tournament that culmina",
      "link": "https://www.theverge.com/tech/881175/red-bull-media-house-game-pop-bulletin-magazine-playable-tetris-flexible-display",
      "published": "2026-02-22T09:03:24-05:00",
      "keywords": [
        "AI",
        "AR",
        "Gaming"
      ],
      "category": "AI/ML",
      "crawled_at": "2026-02-22T18:20:12.718301"
    },
    {
      "source": "theverge",
      "title": "America desperately needs new privacy laws",
      "summary": "This is The Stepback, a weekly newsletter breaking down one essential story from the tech world. For more on the dire state of tech regulation, follow Adi Robertson. The Stepback arrives in our subscribers' inboxes at 8AM ET. Opt in for The Stepback here. How it started In 1973, long before the mode",
      "link": "https://www.theverge.com/column/882516/privacy-laws-america",
      "published": "2026-02-22T08:00:00-05:00",
      "keywords": [
        "AWS",
        "Git",
        "AR"
      ],
      "category": "Cloud/DevOps",
      "crawled_at": "2026-02-22T18:20:12.718341"
    },
    {
      "source": "theverge",
      "title": "Vibe camera shootout: Camp Snap Pro vs. Flashback One35 V2",
      "summary": "There's been a surge of interest over the last few years in inexpensive digital cameras. Younger folks are snapping up old point-and-shoots because they view the aesthetic as more authentic and more appealing than smartphone images. Companies are even rereleasing old tech at new prices. And there ar",
      "link": "https://www.theverge.com/gadgets/882641/camp-snap-pro-flashback-one35-v2-digicam-camera-comparison-review",
      "published": "2026-02-22T08:00:00-05:00",
      "keywords": [
        "REST",
        "Git",
        "AR"
      ],
      "category": "Mobile",
      "crawled_at": "2026-02-22T18:20:12.718385"
    },
    {
      "source": "theverge",
      "title": "Arturia’s FX Collection 6 adds two new effects and a $99 intro version",
      "summary": "Arturia launched a new version of its flagship effects suite, FX Collection, which includes two new plugins, EFX Ambient and Pitch Shifter-910. FX Collection 6 also marks the introduction of an Intro version with a selection of six effects covering the basics for $99. That pales in comparison to the",
      "link": "https://www.theverge.com/tech/882852/arturia-fx-collection-6",
      "published": "2026-02-21T16:10:01-05:00",
      "keywords": [
        "AR"
      ],
      "category": "Tech News",
      "crawled_at": "2026-02-22T18:20:12.718440"
    },
    {
      "source": "hackernews",
      "title": "We hid backdoors in ~40MB binaries and asked AI + Ghidra to find them",
      "summary": "Article URL: https://quesma.com/blog/introducing-binaryaudit/\nComments URL: https://news.ycombinator.com/item?id=47111440\nPoints: 14\n# Comments: 2",
      "link": "https://quesma.com/blog/introducing-binaryaudit/",
      "published": "Sun, 22 Feb 2026 14:50:44 +0000",
      "keywords": [
        "AI",
        "AR"
      ],
      "category": "AI/ML",
      "crawled_at": "2026-02-22T18:20:12.940180"
    },
    {
      "source": "hackernews",
      "title": "Man accidentally gains control of 7k robot vacuums",
      "summary": "Article URL: https://www.popsci.com/technology/robot-vacuum-army/\nComments URL: https://news.ycombinator.com/item?id=47111400\nPoints: 16\n# Comments: 1",
      "link": "https://www.popsci.com/technology/robot-vacuum-army/",
      "published": "Sun, 22 Feb 2026 14:44:42 +0000",
      "keywords": [
        "AI",
        "AR"
      ],
      "category": "AI/ML",
      "crawled_at": "2026-02-22T18:20:12.940217"
    },
    {
      "source": "hackernews",
      "title": "Iran students stage first large anti-government protests since deadly crackdown",
      "summary": "Article URL: https://www.bbc.com/news/articles/c5yj2kzkrj0o\nComments URL: https://news.ycombinator.com/item?id=47111067\nPoints: 25\n# Comments: 4",
      "link": "https://www.bbc.com/news/articles/c5yj2kzkrj0o",
      "published": "Sun, 22 Feb 2026 13:59:40 +0000",
      "keywords": [
        "Go",
        "AR"
      ],
      "category": "Tech News",
      "crawled_at": "2026-02-22T18:20:12.940254"
    },
    {
      "source": "hackernews",
      "title": "I put New Zealand behind a $1 paywall",
      "summary": "Article URL: https://rename.world/\nComments URL: https://news.ycombinator.com/item?id=47111042\nPoints: 22\n# Comments: 4",
      "link": "https://rename.world/",
      "published": "Sun, 22 Feb 2026 13:57:18 +0000",
      "keywords": [
        "AR"
      ],
      "category": "Tech News",
      "crawled_at": "2026-02-22T18:20:12.940285"
    },
    {
      "source": "hackernews",
      "title": "Volatility: The volatile memory forensic extraction framework",
      "summary": "Article URL: https://github.com/volatilityfoundation/volatility3\nComments URL: https://news.ycombinator.com/item?id=47110781\nPoints: 14\n# Comments: 0",
      "link": "https://github.com/volatilityfoundation/volatility3",
      "published": "Sun, 22 Feb 2026 13:20:07 +0000",
      "keywords": [
        "Git",
        "GitHub",
        "AR"
      ],
      "category": "Tech News",
      "crawled_at": "2026-02-22T18:20:12.940320"
    },
    {
      "source": "arstechnica",
      "title": "Study shows how rocket launches pollute the atmosphere",
      "summary": "Is the global atmospheric commons destined to be an industrial waste dumping ground?",
      "link": "https://arstechnica.com/space/2026/02/study-shows-how-rocket-launches-pollute-the-atmosphere/",
      "published": "Sun, 22 Feb 2026 11:20:03 +0000",
      "keywords": [],
      "category": "Tech News",
      "crawled_at": "2026-02-22T18:20:13.113228"
    },
    {
      "source": "arstechnica",
      "title": "NASA says it needs to haul the Artemis II rocket back to the hangar for repairs",
      "summary": "\"Accessing and remediating any of these issues can only be performed in the VAB.\"",
      "link": "https://arstechnica.com/space/2026/02/nasa-says-it-needs-to-haul-the-artemis-ii-rocket-back-to-the-hangar-for-repairs/",
      "published": "Sat, 21 Feb 2026 23:54:38 +0000",
      "keywords": [
        "AI",
        "AR"
      ],
      "category": "AI/ML",
      "crawled_at": "2026-02-22T18:20:13.113259"
    },
    {
      "source": "arstechnica",
      "title": "Dinosaur eggshells can reveal the age of other fossils",
      "summary": "Like rocks, egg shells can trap isotopes, allowing us to use them to date samples.",
      "link": "https://arstechnica.com/science/2026/02/dinosaur-eggshells-can-reveal-the-age-of-other-fossils/",
      "published": "Sat, 21 Feb 2026 13:00:01 +0000",
      "keywords": [],
      "category": "Tech News",
      "crawled_at": "2026-02-22T18:20:13.113287"
    },
    {
      "source": "arstechnica",
      "title": "Have we leapt into commercial genetic testing without understanding it?",
      "summary": "A new book argues that tests might reshape human diversity even if they don't work.",
      "link": "https://arstechnica.com/science/2026/02/have-we-leapt-into-commercial-genetic-testing-without-understanding-it/",
      "published": "Sat, 21 Feb 2026 12:00:56 +0000",
      "keywords": [
        "AR"
      ],
      "category": "Tech News",
      "crawled_at": "2026-02-22T18:20:13.113316"
    },
    {
      "source": "arstechnica",
      "title": "Major government research lab appears to be squeezing out foreign scientists",
      "summary": "\"Noncitizens\" lost after-hours access to a NIST lab last month.",
      "link": "https://arstechnica.com/science/2026/02/major-government-research-lab-appears-to-be-squeezing-out-foreign-scientists/",
      "published": "Sat, 21 Feb 2026 11:31:35 +0000",
      "keywords": [
        "Go",
        "AR"
      ],
      "category": "Mobile",
      "crawled_at": "2026-02-22T18:20:13.113342"
    },
    {
      "source": "wired",
      "title": "What to Know About At-Home STI Tests: Pros, Cons, and Recommendations (2026)",
      "summary": "It's easier than ever to test for sexually transmitted infections at home. We break down whether or not you should.",
      "link": "https://www.wired.com/story/at-home-sti-tests/",
      "published": "Sun, 22 Feb 2026 11:56:00 +0000",
      "keywords": [],
      "category": "Tech News",
      "crawled_at": "2026-02-22T18:20:13.247021"
    },
    {
      "source": "wired",
      "title": "What Is Down Fill Power (2026): Fill Weight, Synthetics",
      "summary": "Whether you’re looking for extra-warm jackets or bedding, you’ve probably seen this term. Let us, er, fill you in.",
      "link": "https://www.wired.com/story/what-is-down-fill-power/",
      "published": "Sun, 22 Feb 2026 11:30:00 +0000",
      "keywords": [
        "AR"
      ],
      "category": "Tech News",
      "crawled_at": "2026-02-22T18:20:13.247075"
    },
    {
      "source": "wired",
      "title": "How to Hide Google’s AI Overviews From Your Search Results",
      "summary": "You can avoid Google’s AI summaries in your search results by simply adjusting your query. Or just switch search engines altogether.",
      "link": "https://www.wired.com/story/how-to-hide-google-ai-overviews-from-your-search-results/",
      "published": "Sun, 22 Feb 2026 11:00:00 +0000",
      "keywords": [
        "AI",
        "Go",
        "Google",
        "AR"
      ],
      "category": "AI/ML",
      "crawled_at": "2026-02-22T18:20:13.247106"
    },
    {
      "source": "wired",
      "title": "Creatine Supplements Are Everywhere. Do I Need Them? (2026)",
      "summary": "It’s the most studied supplement in sports medicine, but it’s not just for athletes anymore.",
      "link": "https://www.wired.com/story/should-you-be-taking-creatine-supplements/",
      "published": "Sun, 22 Feb 2026 10:30:00 +0000",
      "keywords": [
        "AR"
      ],
      "category": "Tech News",
      "crawled_at": "2026-02-22T18:20:13.247141"
    },
    {
      "source": "wired",
      "title": "How to View the ‘Blood Moon’ Total Lunar Eclipse on March 3",
      "summary": "Next month, the Earth will come between the sun and the moon, causing the moon to take on an eerie reddish hue.",
      "link": "https://www.wired.com/story/how-to-view-the-blood-moon-total-lunar-eclipse-on-march-3/",
      "published": "Sun, 22 Feb 2026 10:00:00 +0000",
      "keywords": [
        "AR"
      ],
      "category": "Tech News",
      "crawled_at": "2026-02-22T18:20:13.247176"
    }
  ]
}