{
  "last_updated": "2025-12-05T12:22:17.089746",
  "news_count": 25,
  "news": [
    {
      "source": "techcrunch",
      "title": "Walmart-backed PhonePe winds down its Pincode app in yet another e-commerce step back",
      "summary": "PhonePe has shut down its Pincode app over two years after its debut.",
      "link": "https://techcrunch.com/2025/12/05/walmart-backed-phonepe-winds-down-its-pincode-app-in-yet-another-e-commerce-step-back/",
      "published": "Fri, 05 Dec 2025 11:08:12 +0000",
      "keywords": [
        "AR"
      ],
      "category": "Programming",
      "crawled_at": "2025-12-05T12:22:16.094414"
    },
    {
      "source": "techcrunch",
      "title": "Chicago Tribune sues Perplexity",
      "summary": "The newspaper is alleging copyright infringement and calling out Perplexity's retrieval augmented generation (RAG) as a culprit.",
      "link": "https://techcrunch.com/2025/12/04/chicago-tribune-sues-perplexity/",
      "published": "Fri, 05 Dec 2025 01:20:59 +0000",
      "keywords": [
        "Go"
      ],
      "category": "Tech News",
      "crawled_at": "2025-12-05T12:22:16.094452"
    },
    {
      "source": "techcrunch",
      "title": "All the biggest news from AWS’ big tech show re:Invent 2025",
      "summary": "Amazon Web Services' giant tech conference re:Invent 2025 is happening this week with news ranging from chips to AI services.",
      "link": "https://techcrunch.com/2025/12/04/all-the-biggest-news-from-aws-big-tech-show-reinvent-2025/",
      "published": "Fri, 05 Dec 2025 01:17:08 +0000",
      "keywords": [
        "AI",
        "AWS",
        "Amazon"
      ],
      "category": "AI/ML",
      "crawled_at": "2025-12-05T12:22:16.094485"
    },
    {
      "source": "techcrunch",
      "title": "Feds ask Waymo about robotaxis repeatedly passing school buses in Austin",
      "summary": "The agency already opened an investigation in October over Waymo's performance around school buses. Waymo said it issued a software update to its fleet to improve performance.",
      "link": "https://techcrunch.com/2025/12/04/feds-ask-waymo-about-robotaxis-repeatedly-passing-school-buses-in-austin/",
      "published": "Thu, 04 Dec 2025 22:54:39 +0000",
      "keywords": [
        "AI",
        "AR"
      ],
      "category": "AI/ML",
      "crawled_at": "2025-12-05T12:22:16.094512"
    },
    {
      "source": "techcrunch",
      "title": "Micro1, a Scale AI competitor, touts crossing $100M ARR",
      "summary": "Micro1 started the year with roughly $7 million ARR. Now, it claims to have surpassed $100 million in ARR, double what it reported in September.",
      "link": "https://techcrunch.com/2025/12/04/micro1-a-scale-ai-competitor-touts-crossing-100m-arr/",
      "published": "Thu, 04 Dec 2025 22:45:31 +0000",
      "keywords": [
        "AI",
        "AR"
      ],
      "category": "AI/ML",
      "crawled_at": "2025-12-05T12:22:16.094536"
    },
    {
      "source": "theverge",
      "title": "EU fines X $140 million over ‘deceptive’ blue checkmarks",
      "summary": "The European Union has served Elon Musk’s X with a €120 million (about $140 million) penalty for violating the bloc’s digital service rulebook, in part for the “deceptive design” of its blue checkmark. Today’s announcement marks the first time that a company has been fined under the landmark Digital",
      "link": "https://www.theverge.com/news/645154/eu-fines-x-dsa-violations-xai-elon-musk",
      "published": "2025-12-05T07:04:35-05:00",
      "keywords": [
        "Git",
        "AR"
      ],
      "category": "Tech News",
      "crawled_at": "2025-12-05T12:22:16.290974"
    },
    {
      "source": "theverge",
      "title": "Facebook and Instagram have a new hub to help get hijacked accounts back",
      "summary": "Meta on Thursday announced it is launching a new, centralized support hub for Facebook and Instagram, acknowledging that getting help hasn’t always been as easy as it should be. The space will bring together all the support features users of both networks need to report account issues or recover one",
      "link": "https://www.theverge.com/news/838814/facebook-instagram-hijacked-accounts-hub",
      "published": "2025-12-05T06:08:43-05:00",
      "keywords": [
        "Meta"
      ],
      "category": "Tech News",
      "crawled_at": "2025-12-05T12:22:16.291042"
    },
    {
      "source": "theverge",
      "title": "Microsoft finally has a better looking Run dialog for Windows 11",
      "summary": "Microsoft is finally updating the design of the Run dialog prompt in Windows after more than 30 years. After committing to adding a dark mode to Run, Microsoft is now testing a refreshed design that makes it fit with the aesthetics in Windows 11. X user Phantomofearth discovered the modern Run dialo",
      "link": "https://www.theverge.com/news/838798/microsoft-windows-11-run-dialog-new-ui-dark-mode",
      "published": "2025-12-05T04:53:15-05:00",
      "keywords": [
        "Microsoft",
        "Windows",
        "AR"
      ],
      "category": "Tech News",
      "crawled_at": "2025-12-05T12:22:16.291088"
    },
    {
      "source": "theverge",
      "title": "Netflix wins the bidding war for Warner Bros.",
      "summary": "Netflix is poised to purchase Warner Bros.’ studio and streaming business after being selected as the winner of the bidding war for the media giant. The two companies will now move forward into exclusive deal talks, TheWrap reports, likely including a $5 billion breakup fee in case regulators block ",
      "link": "https://www.theverge.com/news/838781/netflix-warner-bros-discover-bids-buyout",
      "published": "2025-12-05T03:39:02-05:00",
      "keywords": [
        "AR"
      ],
      "category": "Tech News",
      "crawled_at": "2025-12-05T12:22:16.291141"
    },
    {
      "source": "theverge",
      "title": "The best noise-canceling headphones to buy right now",
      "summary": "Whether you’re wearing them for the morning commute, while traveling, or if you’re simply trying to find some peace and quiet while working at home, noise-canceling headphones are a more essential piece of kit nowadays than ever before. And you’ve got a slew of great options to pick from; it’s hard ",
      "link": "https://www.theverge.com/21345733/best-noise-canceling-headphones",
      "published": "2025-12-04T19:58:41-05:00",
      "keywords": [
        "Go",
        "AR"
      ],
      "category": "Tech News",
      "crawled_at": "2025-12-05T12:22:16.291191"
    },
    {
      "source": "hackernews",
      "title": "Why We Can't Quit Excel",
      "summary": "Article URL: https://www.bloomberg.com/features/2025-microsoft-excel-ai-software/\nComments URL: https://news.ycombinator.com/item?id=46159703\nPoints: 13\n# Comments: 18",
      "link": "https://www.bloomberg.com/features/2025-microsoft-excel-ai-software/",
      "published": "Fri, 05 Dec 2025 11:07:07 +0000",
      "keywords": [
        "AI",
        "Microsoft",
        "AR"
      ],
      "category": "AI/ML",
      "crawled_at": "2025-12-05T12:22:16.763446"
    },
    {
      "source": "hackernews",
      "title": "The US polluters that are rewriting the EU's human rights and climate law",
      "summary": "Article URL: https://www.somo.nl/the-secretive-cabal-of-us-polluters-that-is-rewriting-the-eus-human-rights-and-climate-law/\nComments URL: https://news.ycombinator.com/item?id=46159193\nPoints: 263\n# Comments: 131",
      "link": "https://www.somo.nl/the-secretive-cabal-of-us-polluters-that-is-rewriting-the-eus-human-rights-and-climate-law/",
      "published": "Fri, 05 Dec 2025 09:58:01 +0000",
      "keywords": [
        "AR"
      ],
      "category": "Tech News",
      "crawled_at": "2025-12-05T12:22:16.763497"
    },
    {
      "source": "hackernews",
      "title": "Kenyan court declares law banning seed sharing unconstitutional",
      "summary": "Article URL: https://apnews.com/article/kenya-seed-sharing-law-ruling-ad4df5a364299b3a9f8515c0f52d5f80\nComments URL: https://news.ycombinator.com/item?id=46158578\nPoints: 44\n# Comments: 6",
      "link": "https://apnews.com/article/kenya-seed-sharing-law-ruling-ad4df5a364299b3a9f8515c0f52d5f80",
      "published": "Fri, 05 Dec 2025 09:09:25 +0000",
      "keywords": [
        "AR"
      ],
      "category": "Tech News",
      "crawled_at": "2025-12-05T12:22:16.763536"
    },
    {
      "source": "hackernews",
      "title": "Cloudflare Down Again – and DownDetector Is Also Down",
      "summary": "https://downdetector.tr/\n\nComments URL: https://news.ycombinator.com/item?id=46158200\nPoints: 258\n# Comments: 132",
      "link": "https://news.ycombinator.com/item?id=46158200",
      "published": "Fri, 05 Dec 2025 08:51:42 +0000",
      "keywords": [
        "AI",
        "Cloud",
        "AR"
      ],
      "category": "AI/ML",
      "crawled_at": "2025-12-05T12:22:16.763567"
    },
    {
      "source": "hackernews",
      "title": "Cloudflare is down",
      "summary": "Article URL: https://www.cloudflare.com/\nComments URL: https://news.ycombinator.com/item?id=46158191\nPoints: 755\n# Comments: 461",
      "link": "https://www.cloudflare.com/",
      "published": "Fri, 05 Dec 2025 08:50:16 +0000",
      "keywords": [
        "Cloud",
        "AR"
      ],
      "category": "Cloud/DevOps",
      "crawled_at": "2025-12-05T12:22:16.763593"
    },
    {
      "source": "arstechnica",
      "title": "Congress warned that NASA’s current plan for Artemis “cannot work”",
      "summary": "\"The Artemis III mission and those beyond should be canceled.\"",
      "link": "https://arstechnica.com/space/2025/12/congress-told-there-needs-to-be-consequences-for-nasa-delays-amid-chinas-rise/",
      "published": "Thu, 04 Dec 2025 22:54:52 +0000",
      "keywords": [
        "AR"
      ],
      "category": "Tech News",
      "crawled_at": "2025-12-05T12:22:16.984474"
    },
    {
      "source": "arstechnica",
      "title": "In comedy of errors, men accused of wiping gov databases turned to an AI tool",
      "summary": "Defendants were convicted of similar crimes a decade ago. How were they cleared again?",
      "link": "https://arstechnica.com/information-technology/2025/12/previously-convicted-contractors-wiped-gov-databases-after-being-fired-feds-say/",
      "published": "Thu, 04 Dec 2025 21:51:36 +0000",
      "keywords": [
        "AI",
        "Go",
        "Database",
        "AR"
      ],
      "category": "AI/ML",
      "crawled_at": "2025-12-05T12:22:16.984511"
    },
    {
      "source": "arstechnica",
      "title": "Engineer proves that Kohler’s smart toilet cameras aren’t very private",
      "summary": "Kohler is getting the scoop on people's poop.",
      "link": "https://arstechnica.com/gadgets/2025/12/despite-accessing-user-data-kohler-still-says-its-smart-toilet-cameras-use-e2ee/",
      "published": "Thu, 04 Dec 2025 21:23:40 +0000",
      "keywords": [
        "AR"
      ],
      "category": "Tech News",
      "crawled_at": "2025-12-05T12:22:16.984545"
    },
    {
      "source": "arstechnica",
      "title": "CDC vaccine panel realizes again it has no idea what it’s doing, delays big vote",
      "summary": "Today's meeting was chaotic and included garbage anti-vaccine presentations.",
      "link": "https://arstechnica.com/health/2025/12/cdc-vaccine-panel-realizes-again-it-has-no-idea-what-its-doing-delays-big-vote/",
      "published": "Thu, 04 Dec 2025 20:56:44 +0000",
      "keywords": [
        "AI",
        "AR"
      ],
      "category": "AI/ML",
      "crawled_at": "2025-12-05T12:22:16.984573"
    },
    {
      "source": "arstechnica",
      "title": "Researchers find what makes AI chatbots politically persuasive",
      "summary": "A massive study of political persuasion shows AIs have, at best, a weak effect.",
      "link": "https://arstechnica.com/science/2025/12/researchers-find-what-makes-ai-chatbots-politically-persuasive/",
      "published": "Thu, 04 Dec 2025 20:07:20 +0000",
      "keywords": [
        "AI",
        "AR"
      ],
      "category": "AI/ML",
      "crawled_at": "2025-12-05T12:22:16.984594"
    },
    {
      "source": "wired",
      "title": "The Best Meal Replacement Shakes for Total Life Optimization (2025)",
      "summary": "Solve the problem of cooking and chewing food with these full-meal replacement drinks.",
      "link": "https://www.wired.com/gallery/best-liquid-meal-replacements/",
      "published": "Fri, 05 Dec 2025 12:07:00 +0000",
      "keywords": [],
      "category": "Tech News",
      "crawled_at": "2025-12-05T12:22:17.089531"
    },
    {
      "source": "wired",
      "title": "AI Slop Is Ruining Reddit for Everyone",
      "summary": "Reddit is considered one of the most human spaces left on the internet, but mods and users are overwhelmed with slop posts in the most popular subreddits.",
      "link": "https://www.wired.com/story/ai-slop-is-ruining-reddit-for-everyone/",
      "published": "Fri, 05 Dec 2025 12:00:00 +0000",
      "keywords": [
        "AI",
        "AR"
      ],
      "category": "AI/ML",
      "crawled_at": "2025-12-05T12:22:17.089564"
    },
    {
      "source": "wired",
      "title": "How Long Should You Stay in a Sauna? (2025)",
      "summary": "Optimize your sauna session by listening to the experts and, more importantly, your body.",
      "link": "https://www.wired.com/story/how-long-should-you-stay-in-a-sauna/",
      "published": "Fri, 05 Dec 2025 11:30:00 +0000",
      "keywords": [],
      "category": "Tech News",
      "crawled_at": "2025-12-05T12:22:17.089590"
    },
    {
      "source": "wired",
      "title": "Huge Trove of Nude Images Leaked by AI Image Generator Startup’s Exposed Database",
      "summary": "An AI image generator startup’s database was left accessible to the open internet, revealing more than 1 million images and videos, including photos of real people who had been “nudified.”",
      "link": "https://www.wired.com/story/huge-trove-of-nude-images-leaked-by-ai-image-generator-startups-exposed-database/",
      "published": "Fri, 05 Dec 2025 11:00:00 +0000",
      "keywords": [
        "AI",
        "Startup",
        "Database",
        "AR"
      ],
      "category": "AI/ML",
      "crawled_at": "2025-12-05T12:22:17.089629"
    },
    {
      "source": "wired",
      "title": "Logitech Promo Code: $25 Off This Holiday Season",
      "summary": "Get an exclusive discount of $25 off $200+ this holiday season when you sign up for Logitech emails.",
      "link": "https://www.wired.com/story/logitech-promo-code/",
      "published": "Fri, 05 Dec 2025 07:00:00 +0000",
      "keywords": [
        "AI",
        "Git"
      ],
      "category": "AI/ML",
      "crawled_at": "2025-12-05T12:22:17.089666"
    }
  ]
}